{
	"info": {
		"_postman_id": "eba8f82e-0cc1-44d6-84f6-88c31f3a5e12",
		"name": "Scala Play Crud Example",
		"schema": "https://schema.getpostman.com/json/collection/v2.1.0/collection.json"
	},
	"item": [
		{
			"name": "Init",
			"request": {
				"method": "GET",
				"header": [],
				"url": {
					"raw": "localhost:9000/init",
					"host": [
						"localhost"
					],
					"port": "9000",
					"path": [
						"init"
					]
				}
			},
			"response": []
		},
		{
			"name": "Add artist",
			"request": {
				"method": "POST",
				"header": [],
				"body": {
					"mode": "raw",
					"raw": "{\n    \"name\": \"Coma\"\n}",
					"options": {
						"raw": {
							"language": "json"
						}
					}
				},
				"url": {
					"raw": "localhost:9000/artist",
					"host": [
						"localhost"
					],
					"port": "9000",
					"path": [
						"artist"
					]
				}
			},
			"response": []
		},
		{
			"name": "Get all artists",
			"request": {
				"method": "GET",
				"header": [],
				"url": {
					"raw": "localhost:9000/artist",
					"host": [
						"localhost"
					],
					"port": "9000",
					"path": [
						"artist"
					]
				}
			},
			"response": []
		},
		{
			"name": "Get artist by id",
			"request": {
				"method": "GET",
				"header": [],
				"url": {
					"raw": "localhost:9000/artist/0",
					"host": [
						"localhost"
					],
					"port": "9000",
					"path": [
						"artist",
						"0"
					]
				}
			},
			"response": []
		},
		{
			"name": "Delete artist",
			"request": {
				"method": "DELETE",
				"header": [],
				"url": {
					"raw": "localhost:9000/artist/0",
					"host": [
						"localhost"
					],
					"port": "9000",
					"path": [
						"artist",
						"0"
					]
				}
			},
			"response": []
		},
		{
			"name": "Update artist",
			"request": {
				"method": "PUT",
				"header": [],
				"body": {
					"mode": "raw",
					"raw": "{\n    \"name\": \"Coma 3\"\n}",
					"options": {
						"raw": {
							"language": "json"
						}
					}
				},
				"url": {
					"raw": "localhost:9000/artist/0",
					"host": [
						"localhost"
					],
					"port": "9000",
					"path": [
						"artist",
						"0"
					]
				}
			},
			"response": []
		},
		{
			"name": "Add album",
			"request": {
				"method": "POST",
				"header": [],
				"body": {
					"mode": "raw",
					"raw": "{\n  \"name\": \"asd\",\n  \"artistId\": 0  \n}",
					"options": {
						"raw": {
							"language": "json"
						}
					}
				},
				"url": {
					"raw": "localhost:9000/album/0",
					"host": [
						"localhost"
					],
					"port": "9000",
					"path": [
						"album",
						"0"
					]
				}
			},
			"response": []
		},
		{
			"name": "Get all albums",
			"request": {
				"method": "GET",
				"header": [],
				"url": {
					"raw": "localhost:9000/album",
					"host": [
						"localhost"
					],
					"port": "9000",
					"path": [
						"album"
					]
				}
			},
			"response": []
		},
		{
			"name": "Get album by id",
			"request": {
				"method": "GET",
				"header": [],
				"url": {
					"raw": "localhost:9000/album/0",
					"host": [
						"localhost"
					],
					"port": "9000",
					"path": [
						"album",
						"0"
					]
				}
			},
			"response": []
		},
		{
			"name": "Update album",
			"request": {
				"method": "PUT",
				"header": [],
				"body": {
					"mode": "raw",
					"raw": "{\n    \"name\": \"Czerwony album 2\",\n    \"artistId\": 2\n}",
					"options": {
						"raw": {
							"language": "json"
						}
					}
				},
				"url": {
					"raw": "localhost:9000/album/3",
					"host": [
						"localhost"
					],
					"port": "9000",
					"path": [
						"album",
						"3"
					]
				}
			},
			"response": []
		},
		{
			"name": "Delete album",
			"request": {
				"method": "DELETE",
				"header": [],
				"body": {
					"mode": "raw",
					"raw": "{\n    \"name\": \"Czerwony album 2\",\n    \"artistId\": 2\n}",
					"options": {
						"raw": {
							"language": "json"
						}
					}
				},
				"url": {
					"raw": "localhost:9000/album/3",
					"host": [
						"localhost"
					],
					"port": "9000",
					"path": [
						"album",
						"3"
					]
				}
			},
			"response": []
		},
		{
			"name": "Add song",
			"request": {
				"method": "POST",
				"header": [],
				"body": {
					"mode": "raw",
					"raw": "{\n    \"title\": \"ADS\",\n    \"albumId\": 0\n}",
					"options": {
						"raw": {
							"language": "json"
						}
					}
				},
				"url": {
					"raw": "localhost:9000/song",
					"host": [
						"localhost"
					],
					"port": "9000",
					"path": [
						"song"
					]
				}
			},
			"response": []
		},
		{
			"name": "Get all songs",
			"request": {
				"method": "GET",
				"header": [],
				"url": {
					"raw": "localhost:9000/song",
					"host": [
						"localhost"
					],
					"port": "9000",
					"path": [
						"song"
					]
				}
			},
			"response": []
		},
		{
			"name": "Get song by id",
			"request": {
				"method": "GET",
				"header": [],
				"url": {
					"raw": "localhost:9000/song/0",
					"host": [
						"localhost"
					],
					"port": "9000",
					"path": [
						"song",
						"0"
					]
				}
			},
			"response": []
		},
		{
			"name": "Update song",
			"request": {
				"method": "PUT",
				"header": [],
				"body": {
					"mode": "raw",
					"raw": "{\n    \"title\": \"Los cebula i krokodyle łzy 2\",\n    \"albumId\": 4\n}",
					"options": {
						"raw": {
							"language": "json"
						}
					}
				},
				"url": {
					"raw": "localhost:9000/song/6",
					"host": [
						"localhost"
					],
					"port": "9000",
					"path": [
						"song",
						"6"
					]
				}
			},
			"response": []
		},
		{
			"name": "Delete song",
			"request": {
				"method": "DELETE",
				"header": [],
				"url": {
					"raw": "localhost:9000/song/0",
					"host": [
						"localhost"
					],
					"port": "9000",
					"path": [
						"song",
						"0"
					]
				}
			},
			"response": []
		}
	]
}